{
  "objectInfo" : {
    "id" : "6Ng9PC3EPPtbBW9G8510Sv",
    "name" : "Project_With_Dependencies_PullByCommitHash",
    "type" : "Project",
    "metadata" : {
      "modelVersion" : {
        "major" : 0,
        "minor" : 0
      },
      "repoInfo" : null,
      "contextAttributes" : [ ],
      "additionalInfo" : {
        "description" : "",
        "contentType" : "Binary",
        "documentState" : "COMPLETE"
      }
    }
  },
  "dataFileExtension" : "json",
  "updateTime" : "2023-08-25T21:40:23.844Z",
  "objectRefs" : [ ]
}